{
  "snapshots": [
    {
      "date": "2026-03-16",
      "run_number": 1,
      "total_pageviews": 454042,
      "total_users": 390072,
      "total_sessions": 430923,
      "new_users": 327622,
      "subscriber_events": 98,
      "top_source": {
        "source": "hs_email",
        "medium": "email",
        "pct": 0.422
      },
      "top_article": {
        "path": "/2026/01/20/2m-deal-near-burnham-yard-suggests-broncos-may-be-thinking-bigger-than-known/",
        "pageviews": 13471
      },
      "article_count": 16460
    },
    {
      "date": "2026-03-16",
      "run_number": 2,
      "total_pageviews": 454056,
      "total_users": 390086,
      "total_sessions": 430937,
      "new_users": 327635,
      "subscriber_events": 98,
      "top_source": {
        "source": "hs_email",
        "medium": "email",
        "pct": 0.422
      },
      "top_article": {
        "path": "/2026/01/20/2m-deal-near-burnham-yard-suggests-broncos-may-be-thinking-bigger-than-known/",
        "pageviews": 13471
      },
      "article_count": 16460
    },
    {
      "date": "2026-03-16",
      "run_number": 3,
      "total_pageviews": 454056,
      "total_users": 390086,
      "total_sessions": 430937,
      "new_users": 327635,
      "subscriber_events": 98,
      "top_source": {
        "source": "hs_email",
        "medium": "email",
        "pct": 0.422
      },
      "top_article": {
        "path": "/2026/01/20/2m-deal-near-burnham-yard-suggests-broncos-may-be-thinking-bigger-than-known/",
        "pageviews": 13471
      },
      "article_count": 16460
    },
    {
      "date": "2026-03-16",
      "run_number": 4,
      "total_pageviews": 454056,
      "total_users": 390086,
      "total_sessions": 430937,
      "new_users": 327635,
      "subscriber_events": 98,
      "top_source": {
        "source": "hs_email",
        "medium": "email",
        "pct": 0.422
      },
      "top_article": {
        "path": "/2026/01/20/2m-deal-near-burnham-yard-suggests-broncos-may-be-thinking-bigger-than-known/",
        "pageviews": 13471
      },
      "article_count": 16460
    },
    {
      "date": "2026-03-17",
      "run_number": 5,
      "total_pageviews": 458776,
      "total_users": 394027,
      "total_sessions": 435385,
      "new_users": 330100,
      "subscriber_events": 100,
      "top_source": {
        "source": "hs_email",
        "medium": "email",
        "pct": 0.4246
      },
      "top_article": {
        "path": "/2026/01/20/2m-deal-near-burnham-yard-suggests-broncos-may-be-thinking-bigger-than-known/",
        "pageviews": 13471
      },
      "article_count": 16466
    },
    {
      "date": "2026-03-17",
      "run_number": 6,
      "total_pageviews": 452913,
      "total_users": 389119,
      "total_sessions": 429859,
      "new_users": 326755,
      "subscriber_events": 99,
      "top_source": {
        "source": "hs_email",
        "medium": "email",
        "pct": 0.4238
      },
      "top_article": {
        "path": "/2026/01/20/2m-deal-near-burnham-yard-suggests-broncos-may-be-thinking-bigger-than-known/",
        "pageviews": 13471
      },
      "article_count": 16345
    },
    {
      "date": "2026-03-18",
      "run_number": 7,
      "total_pageviews": 453435,
      "total_users": 389590,
      "total_sessions": 430348,
      "new_users": 327881,
      "subscriber_events": 100,
      "top_source": {
        "source": "hs_email",
        "medium": "email",
        "pct": 0.4237
      },
      "top_article": {
        "path": "/2026/01/20/2m-deal-near-burnham-yard-suggests-broncos-may-be-thinking-bigger-than-known/",
        "pageviews": 13471
      },
      "article_count": 16275
    },
    {
      "date": "2026-03-19",
      "run_number": 8,
      "total_pageviews": 455669,
      "total_users": 391633,
      "total_sessions": 432411,
      "new_users": 329964,
      "subscriber_events": 101,
      "top_source": {
        "source": "hs_email",
        "medium": "email",
        "pct": 0.4222
      },
      "top_article": {
        "path": "/2026/01/20/2m-deal-near-burnham-yard-suggests-broncos-may-be-thinking-bigger-than-known/",
        "pageviews": 13471
      },
      "article_count": 16200
    },
    {
      "date": "2026-03-20",
      "run_number": 9,
      "total_pageviews": 457910,
      "total_users": 393518,
      "total_sessions": 434492,
      "new_users": 331689,
      "subscriber_events": 102,
      "top_source": {
        "source": "hs_email",
        "medium": "email",
        "pct": 0.421
      },
      "top_article": {
        "path": "/2026/01/20/2m-deal-near-burnham-yard-suggests-broncos-may-be-thinking-bigger-than-known/",
        "pageviews": 13471
      },
      "article_count": 16108
    },
    {
      "date": "2026-03-21",
      "run_number": 10,
      "total_pageviews": 461650,
      "total_users": 396573,
      "total_sessions": 438064,
      "new_users": 332593,
      "subscriber_events": 103,
      "top_source": {
        "source": "hs_email",
        "medium": "email",
        "pct": 0.4244
      },
      "top_article": {
        "path": "/2026/01/20/2m-deal-near-burnham-yard-suggests-broncos-may-be-thinking-bigger-than-known/",
        "pageviews": 13471
      },
      "article_count": 16028
    },
    {
      "date": "2026-03-22",
      "run_number": 11,
      "total_pageviews": 462160,
      "total_users": 396969,
      "total_sessions": 438507,
      "new_users": 333100,
      "subscriber_events": 103,
      "top_source": {
        "source": "hs_email",
        "medium": "email",
        "pct": 0.4243
      },
      "top_article": {
        "path": "/2026/01/20/2m-deal-near-burnham-yard-suggests-broncos-may-be-thinking-bigger-than-known/",
        "pageviews": 13471
      },
      "article_count": 15982
    },
    {
      "date": "2026-03-23",
      "run_number": 12,
      "total_pageviews": 454409,
      "total_users": 390049,
      "total_sessions": 431129,
      "new_users": 327854,
      "subscriber_events": 103,
      "top_source": {
        "source": "hs_email",
        "medium": "email",
        "pct": 0.4257
      },
      "top_article": {
        "path": "/2026/01/20/2m-deal-near-burnham-yard-suggests-broncos-may-be-thinking-bigger-than-known/",
        "pageviews": 13472
      },
      "article_count": 15953
    },
    {
      "date": "2026-03-24",
      "run_number": 13,
      "total_pageviews": 455250,
      "total_users": 390684,
      "total_sessions": 431856,
      "new_users": 328132,
      "subscriber_events": 105,
      "top_source": {
        "source": "hs_email",
        "medium": "email",
        "pct": 0.4256
      },
      "top_article": {
        "path": "/2026/01/20/2m-deal-near-burnham-yard-suggests-broncos-may-be-thinking-bigger-than-known/",
        "pageviews": 13476
      },
      "article_count": 15934
    },
    {
      "date": "2026-03-25",
      "run_number": 14,
      "total_pageviews": 456678,
      "total_users": 391782,
      "total_sessions": 433229,
      "new_users": 328642,
      "subscriber_events": 105,
      "top_source": {
        "source": "hs_email",
        "medium": "email",
        "pct": 0.4258
      },
      "top_article": {
        "path": "/2026/01/20/2m-deal-near-burnham-yard-suggests-broncos-may-be-thinking-bigger-than-known/",
        "pageviews": 13478
      },
      "article_count": 15929
    },
    {
      "date": "2026-03-26",
      "run_number": 15,
      "total_pageviews": 460890,
      "total_users": 395220,
      "total_sessions": 437266,
      "new_users": 330494,
      "subscriber_events": 106,
      "top_source": {
        "source": "hs_email",
        "medium": "email",
        "pct": 0.4283
      },
      "top_article": {
        "path": "/2026/01/20/2m-deal-near-burnham-yard-suggests-broncos-may-be-thinking-bigger-than-known/",
        "pageviews": 13479
      },
      "article_count": 15936
    },
    {
      "date": "2026-03-27",
      "run_number": 16,
      "total_pageviews": 464698,
      "total_users": 398372,
      "total_sessions": 440912,
      "new_users": 332511,
      "subscriber_events": 107,
      "top_source": {
        "source": "hs_email",
        "medium": "email",
        "pct": 0.4296
      },
      "top_article": {
        "path": "/2026/01/20/2m-deal-near-burnham-yard-suggests-broncos-may-be-thinking-bigger-than-known/",
        "pageviews": 13479
      },
      "article_count": 15943
    },
    {
      "date": "2026-03-28",
      "run_number": 17,
      "total_pageviews": 468577,
      "total_users": 401592,
      "total_sessions": 444671,
      "new_users": 334400,
      "subscriber_events": 108,
      "top_source": {
        "source": "hs_email",
        "medium": "email",
        "pct": 0.4317
      },
      "top_article": {
        "path": "/2026/01/20/2m-deal-near-burnham-yard-suggests-broncos-may-be-thinking-bigger-than-known/",
        "pageviews": 13481
      },
      "article_count": 15947
    },
    {
      "date": "2026-03-29",
      "run_number": 18,
      "total_pageviews": 469578,
      "total_users": 402493,
      "total_sessions": 445621,
      "new_users": 335437,
      "subscriber_events": 108,
      "top_source": {
        "source": "hs_email",
        "medium": "email",
        "pct": 0.431
      },
      "top_article": {
        "path": "/2026/01/20/2m-deal-near-burnham-yard-suggests-broncos-may-be-thinking-bigger-than-known/",
        "pageviews": 13481
      },
      "article_count": 15948
    },
    {
      "date": "2026-03-30",
      "run_number": 19,
      "total_pageviews": 465303,
      "total_users": 398945,
      "total_sessions": 441733,
      "new_users": 333411,
      "subscriber_events": 107,
      "top_source": {
        "source": "hs_email",
        "medium": "email",
        "pct": 0.4287
      },
      "top_article": {
        "path": "/2026/01/20/2m-deal-near-burnham-yard-suggests-broncos-may-be-thinking-bigger-than-known/",
        "pageviews": 13481
      },
      "article_count": 15883
    },
    {
      "date": "2026-03-31",
      "run_number": 20,
      "total_pageviews": 464954,
      "total_users": 398193,
      "total_sessions": 441298,
      "new_users": 331062,
      "subscriber_events": 111,
      "top_source": {
        "source": "hs_email",
        "medium": "email",
        "pct": 0.4323
      },
      "top_article": {
        "path": "/2026/01/20/2m-deal-near-burnham-yard-suggests-broncos-may-be-thinking-bigger-than-known/",
        "pageviews": 13481
      },
      "article_count": 15530
    },
    {
      "date": "2026-04-01",
      "run_number": 21,
      "total_pageviews": 466327,
      "total_users": 399175,
      "total_sessions": 442576,
      "new_users": 330224,
      "subscriber_events": 112,
      "top_source": {
        "source": "hs_email",
        "medium": "email",
        "pct": 0.434
      },
      "top_article": {
        "path": "/2026/01/20/2m-deal-near-burnham-yard-suggests-broncos-may-be-thinking-bigger-than-known/",
        "pageviews": 13481
      },
      "article_count": 15230
    },
    {
      "date": "2026-04-02",
      "run_number": 22,
      "total_pageviews": 469636,
      "total_users": 401852,
      "total_sessions": 445784,
      "new_users": 330283,
      "subscriber_events": 113,
      "top_source": {
        "source": "hs_email",
        "medium": "email",
        "pct": 0.437
      },
      "top_article": {
        "path": "/2026/01/20/2m-deal-near-burnham-yard-suggests-broncos-may-be-thinking-bigger-than-known/",
        "pageviews": 13481
      },
      "article_count": 14993
    },
    {
      "date": "2026-04-03",
      "run_number": 23,
      "total_pageviews": 475259,
      "total_users": 406591,
      "total_sessions": 451058,
      "new_users": 332692,
      "subscriber_events": 114,
      "top_source": {
        "source": "hs_email",
        "medium": "email",
        "pct": 0.4375
      },
      "top_article": {
        "path": "/2026/01/20/2m-deal-near-burnham-yard-suggests-broncos-may-be-thinking-bigger-than-known/",
        "pageviews": 13481
      },
      "article_count": 14906
    },
    {
      "date": "2026-04-04",
      "run_number": 24,
      "total_pageviews": 480275,
      "total_users": 410564,
      "total_sessions": 455563,
      "new_users": 334481,
      "subscriber_events": 115,
      "top_source": {
        "source": "hs_email",
        "medium": "email",
        "pct": 0.4393
      },
      "top_article": {
        "path": "/2026/01/20/2m-deal-near-burnham-yard-suggests-broncos-may-be-thinking-bigger-than-known/",
        "pageviews": 13481
      },
      "article_count": 14834
    },
    {
      "date": "2026-04-05",
      "run_number": 25,
      "total_pageviews": 479652,
      "total_users": 409762,
      "total_sessions": 454943,
      "new_users": 333393,
      "subscriber_events": 115,
      "top_source": {
        "source": "hs_email",
        "medium": "email",
        "pct": 0.4404
      },
      "top_article": {
        "path": "/2026/01/20/2m-deal-near-burnham-yard-suggests-broncos-may-be-thinking-bigger-than-known/",
        "pageviews": 13482
      },
      "article_count": 14768
    },
    {
      "date": "2026-04-06",
      "run_number": 26,
      "total_pageviews": 473806,
      "total_users": 405034,
      "total_sessions": 449516,
      "new_users": 331009,
      "subscriber_events": 113,
      "top_source": {
        "source": "hs_email",
        "medium": "email",
        "pct": 0.4374
      },
      "top_article": {
        "path": "/2026/01/20/2m-deal-near-burnham-yard-suggests-broncos-may-be-thinking-bigger-than-known/",
        "pageviews": 13482
      },
      "article_count": 14748
    },
    {
      "date": "2026-04-07",
      "run_number": 27,
      "total_pageviews": 476529,
      "total_users": 407718,
      "total_sessions": 452226,
      "new_users": 333291,
      "subscriber_events": 112,
      "top_source": {
        "source": "hs_email",
        "medium": "email",
        "pct": 0.4349
      },
      "top_article": {
        "path": "/2026/01/20/2m-deal-near-burnham-yard-suggests-broncos-may-be-thinking-bigger-than-known/",
        "pageviews": 13482
      },
      "article_count": 14745
    },
    {
      "date": "2026-04-08",
      "run_number": 28,
      "total_pageviews": 475312,
      "total_users": 406579,
      "total_sessions": 450973,
      "new_users": 332749,
      "subscriber_events": 116,
      "top_source": {
        "source": "hs_email",
        "medium": "email",
        "pct": 0.4343
      },
      "top_article": {
        "path": "/2026/01/20/2m-deal-near-burnham-yard-suggests-broncos-may-be-thinking-bigger-than-known/",
        "pageviews": 13482
      },
      "article_count": 14721
    },
    {
      "date": "2026-04-09",
      "run_number": 29,
      "total_pageviews": 473091,
      "total_users": 404791,
      "total_sessions": 448796,
      "new_users": 331872,
      "subscriber_events": 116,
      "top_source": {
        "source": "hs_email",
        "medium": "email",
        "pct": 0.434
      },
      "top_article": {
        "path": "/2026/01/20/2m-deal-near-burnham-yard-suggests-broncos-may-be-thinking-bigger-than-known/",
        "pageviews": 13482
      },
      "article_count": 14703
    },
    {
      "date": "2026-04-10",
      "run_number": 30,
      "total_pageviews": 474921,
      "total_users": 406753,
      "total_sessions": 450677,
      "new_users": 334202,
      "subscriber_events": 117,
      "top_source": {
        "source": "hs_email",
        "medium": "email",
        "pct": 0.4314
      },
      "top_article": {
        "path": "/2026/01/20/2m-deal-near-burnham-yard-suggests-broncos-may-be-thinking-bigger-than-known/",
        "pageviews": 13482
      },
      "article_count": 14705
    },
    {
      "date": "2026-04-11",
      "run_number": 31,
      "total_pageviews": 479851,
      "total_users": 410994,
      "total_sessions": 455469,
      "new_users": 337064,
      "subscriber_events": 116,
      "top_source": {
        "source": "hs_email",
        "medium": "email",
        "pct": 0.4346
      },
      "top_article": {
        "path": "/2026/01/20/2m-deal-near-burnham-yard-suggests-broncos-may-be-thinking-bigger-than-known/",
        "pageviews": 13482
      },
      "article_count": 14711
    },
    {
      "date": "2026-04-12",
      "run_number": 32,
      "total_pageviews": 480835,
      "total_users": 411884,
      "total_sessions": 456415,
      "new_users": 338286,
      "subscriber_events": 115,
      "top_source": {
        "source": "hs_email",
        "medium": "email",
        "pct": 0.4341
      },
      "top_article": {
        "path": "/2026/01/20/2m-deal-near-burnham-yard-suggests-broncos-may-be-thinking-bigger-than-known/",
        "pageviews": 13484
      },
      "article_count": 14719
    },
    {
      "date": "2026-04-13",
      "run_number": 33,
      "total_pageviews": 474301,
      "total_users": 406261,
      "total_sessions": 450165,
      "new_users": 334173,
      "subscriber_events": 114,
      "top_source": {
        "source": "hs_email",
        "medium": "email",
        "pct": 0.4318
      },
      "top_article": {
        "path": "/2026/01/20/2m-deal-near-burnham-yard-suggests-broncos-may-be-thinking-bigger-than-known/",
        "pageviews": 13484
      },
      "article_count": 14645
    },
    {
      "date": "2026-04-14",
      "run_number": 34,
      "total_pageviews": 473813,
      "total_users": 405727,
      "total_sessions": 449592,
      "new_users": 333469,
      "subscriber_events": 113,
      "top_source": {
        "source": "hs_email",
        "medium": "email",
        "pct": 0.4329
      },
      "top_article": {
        "path": "/2026/01/20/2m-deal-near-burnham-yard-suggests-broncos-may-be-thinking-bigger-than-known/",
        "pageviews": 13484
      },
      "article_count": 14582
    },
    {
      "date": "2026-04-15",
      "run_number": 35,
      "total_pageviews": 474302,
      "total_users": 406055,
      "total_sessions": 450031,
      "new_users": 333470,
      "subscriber_events": 111,
      "top_source": {
        "source": "hs_email",
        "medium": "email",
        "pct": 0.4323
      },
      "top_article": {
        "path": "/2026/01/20/2m-deal-near-burnham-yard-suggests-broncos-may-be-thinking-bigger-than-known/",
        "pageviews": 13484
      },
      "article_count": 14527
    },
    {
      "date": "2026-04-16",
      "run_number": 36,
      "total_pageviews": 475906,
      "total_users": 407240,
      "total_sessions": 451396,
      "new_users": 333867,
      "subscriber_events": 112,
      "top_source": {
        "source": "hs_email",
        "medium": "email",
        "pct": 0.4321
      },
      "top_article": {
        "path": "/2026/01/20/2m-deal-near-burnham-yard-suggests-broncos-may-be-thinking-bigger-than-known/",
        "pageviews": 13484
      },
      "article_count": 14450
    }
  ]
}